[
    {
        "data": {
            "author_id": "145205455",
            "conversation_id": "1128153247162740737",
            "entities": {
                "urls": [
                    {
                        "start": 0,
                        "end": 23,
                        "url": "https://t.co/F15bOLJWSu",
                        "expanded_url": "https://www.scmp.com/week-asia/politics/article/3009407/singapore-playing-time-water-dispute-malaysia-daim-zainuddin?ch=2&share=92c97739",
                        "display_url": "scmp.com/week-asia/poli\u2026"
                    }
                ]
            },
            "lang": "und",
            "created_at": "2019-05-14T04:21:08.000Z",
            "public_metrics": {
                "retweet_count": 0,
                "reply_count": 0,
                "like_count": 0,
                "quote_count": 0
            },
            "id": "1128153247162740737",
            "text": "https://t.co/F15bOLJWSu",
            "source": "Twitter for iPhone",
            "possibly_sensitive": false,
            "reply_settings": "everyone"
        },
        "id": 1128153247162740737,
        "text": "https://t.co/F15bOLJWSu",
        "attachments": null,
        "author_id": 145205455,
        "context_annotations": [],
        "conversation_id": 1128153247162740737,
        "created_at": "2019-05-14T04:21:08+00:00",
        "entities": {
            "urls": [
                {
                    "start": 0,
                    "end": 23,
                    "url": "https://t.co/F15bOLJWSu",
                    "expanded_url": "https://www.scmp.com/week-asia/politics/article/3009407/singapore-playing-time-water-dispute-malaysia-daim-zainuddin?ch=2&share=92c97739",
                    "display_url": "scmp.com/week-asia/poli\u2026"
                }
            ]
        },
        "geo": null,
        "in_reply_to_user_id": null,
        "lang": "und",
        "non_public_metrics": null,
        "organic_metrics": null,
        "possibly_sensitive": false,
        "promoted_metrics": null,
        "public_metrics": {
            "retweet_count": 0,
            "reply_count": 0,
            "like_count": 0,
            "quote_count": 0
        },
        "referenced_tweets": null,
        "reply_settings": "everyone",
        "source": "Twitter for iPhone",
        "withheld": null
    },
    {
        "data": {
            "author_id": "15099706",
            "conversation_id": "1127400253886537729",
            "entities": {
                "urls": [
                    {
                        "start": 137,
                        "end": 160,
                        "url": "https://t.co/yHfo3w7mFD",
                        "expanded_url": "https://www.scmp.com/week-asia/politics/article/3009407/singapore-playing-time-water-dispute-malaysia-daim-zainuddin?utm_medium=Social&utm_source=Facebook#Echobox=1557483698",
                        "display_url": "scmp.com/week-asia/poli\u2026"
                    }
                ],
                "annotations": [
                    {
                        "start": 36,
                        "end": 44,
                        "probability": 0.9228,
                        "type": "Place",
                        "normalized_text": "Singapore"
                    }
                ]
            },
            "lang": "en",
            "created_at": "2019-05-12T02:29:01.000Z",
            "public_metrics": {
                "retweet_count": 0,
                "reply_count": 0,
                "like_count": 0,
                "quote_count": 0
            },
            "id": "1127400253886537729",
            "text": "A Malaysian government adviser says Singapore may be using a delaying tactic as it heads towards self-sufficiency in its water supplies. https://t.co/yHfo3w7mFD",
            "source": "Facebook",
            "possibly_sensitive": false,
            "reply_settings": "everyone"
        },
        "id": 1127400253886537729,
        "text": "A Malaysian government adviser says Singapore may be using a delaying tactic as it heads towards self-sufficiency in its water supplies. https://t.co/yHfo3w7mFD",
        "attachments": null,
        "author_id": 15099706,
        "context_annotations": [],
        "conversation_id": 1127400253886537729,
        "created_at": "2019-05-12T02:29:01+00:00",
        "entities": {
            "urls": [
                {
                    "start": 137,
                    "end": 160,
                    "url": "https://t.co/yHfo3w7mFD",
                    "expanded_url": "https://www.scmp.com/week-asia/politics/article/3009407/singapore-playing-time-water-dispute-malaysia-daim-zainuddin?utm_medium=Social&utm_source=Facebook#Echobox=1557483698",
                    "display_url": "scmp.com/week-asia/poli\u2026"
                }
            ],
            "annotations": [
                {
                    "start": 36,
                    "end": 44,
                    "probability": 0.9228,
                    "type": "Place",
                    "normalized_text": "Singapore"
                }
            ]
        },
        "geo": null,
        "in_reply_to_user_id": null,
        "lang": "en",
        "non_public_metrics": null,
        "organic_metrics": null,
        "possibly_sensitive": false,
        "promoted_metrics": null,
        "public_metrics": {
            "retweet_count": 0,
            "reply_count": 0,
            "like_count": 0,
            "quote_count": 0
        },
        "referenced_tweets": null,
        "reply_settings": "everyone",
        "source": "Facebook",
        "withheld": null
    },
    {
        "data": {
            "author_id": "75342251",
            "conversation_id": "1126508219814240257",
            "entities": {
                "urls": [
                    {
                        "start": 86,
                        "end": 109,
                        "url": "https://t.co/AYh6iJQJxs",
                        "expanded_url": "https://singaporeinformer.com/361166/singapore-playing-for-time-in-water-dispute-with-malaysia-daim-zainuddin-asiaone/",
                        "display_url": "singaporeinformer.com/361166/singapo\u2026"
                    },
                    {
                        "start": 110,
                        "end": 133,
                        "url": "https://t.co/2v71kkELEw",
                        "expanded_url": "https://twitter.com/singaporeinform/status/1126508219814240257/photo/1",
                        "display_url": "pic.twitter.com/2v71kkELEw"
                    }
                ],
                "annotations": [
                    {
                        "start": 0,
                        "end": 8,
                        "probability": 0.8974,
                        "type": "Place",
                        "normalized_text": "Singapore"
                    },
                    {
                        "start": 51,
                        "end": 58,
                        "probability": 0.9745,
                        "type": "Place",
                        "normalized_text": "Malaysia"
                    },
                    {
                        "start": 61,
                        "end": 74,
                        "probability": 0.8925,
                        "type": "Person",
                        "normalized_text": "Daim Zainuddin"
                    }
                ]
            },
            "lang": "en",
            "created_at": "2019-05-09T15:24:23.000Z",
            "public_metrics": {
                "retweet_count": 0,
                "reply_count": 0,
                "like_count": 0,
                "quote_count": 0
            },
            "id": "1126508219814240257",
            "text": "Singapore \u2018playing for time\u2019 in water dispute with Malaysia: Daim Zainuddin \u2013\u00a0AsiaOne https://t.co/AYh6iJQJxs https://t.co/2v71kkELEw",
            "source": "WordPress.com",
            "possibly_sensitive": false,
            "attachments": {
                "media_keys": [
                    "3_1126508217545003008"
                ]
            },
            "reply_settings": "everyone"
        },
        "id": 1126508219814240257,
        "text": "Singapore \u2018playing for time\u2019 in water dispute with Malaysia: Daim Zainuddin \u2013\u00a0AsiaOne https://t.co/AYh6iJQJxs https://t.co/2v71kkELEw",
        "attachments": {
            "media_keys": [
                "3_1126508217545003008"
            ]
        },
        "author_id": 75342251,
        "context_annotations": [],
        "conversation_id": 1126508219814240257,
        "created_at": "2019-05-09T15:24:23+00:00",
        "entities": {
            "urls": [
                {
                    "start": 86,
                    "end": 109,
                    "url": "https://t.co/AYh6iJQJxs",
                    "expanded_url": "https://singaporeinformer.com/361166/singapore-playing-for-time-in-water-dispute-with-malaysia-daim-zainuddin-asiaone/",
                    "display_url": "singaporeinformer.com/361166/singapo\u2026"
                },
                {
                    "start": 110,
                    "end": 133,
                    "url": "https://t.co/2v71kkELEw",
                    "expanded_url": "https://twitter.com/singaporeinform/status/1126508219814240257/photo/1",
                    "display_url": "pic.twitter.com/2v71kkELEw"
                }
            ],
            "annotations": [
                {
                    "start": 0,
                    "end": 8,
                    "probability": 0.8974,
                    "type": "Place",
                    "normalized_text": "Singapore"
                },
                {
                    "start": 51,
                    "end": 58,
                    "probability": 0.9745,
                    "type": "Place",
                    "normalized_text": "Malaysia"
                },
                {
                    "start": 61,
                    "end": 74,
                    "probability": 0.8925,
                    "type": "Person",
                    "normalized_text": "Daim Zainuddin"
                }
            ]
        },
        "geo": null,
        "in_reply_to_user_id": null,
        "lang": "en",
        "non_public_metrics": null,
        "organic_metrics": null,
        "possibly_sensitive": false,
        "promoted_metrics": null,
        "public_metrics": {
            "retweet_count": 0,
            "reply_count": 0,
            "like_count": 0,
            "quote_count": 0
        },
        "referenced_tweets": null,
        "reply_settings": "everyone",
        "source": "WordPress.com",
        "withheld": null
    },
    {
        "data": {
            "author_id": "19013879",
            "conversation_id": "1126476044918300672",
            "entities": {
                "urls": [
                    {
                        "start": 76,
                        "end": 99,
                        "url": "https://t.co/73vF8bogTx",
                        "expanded_url": "https://www.asiaone.com/singapore/singapore-playing-time-water-dispute-malaysia-daim-zainuddin?utm_term=Autofeed&utm_medium=Social&utm_source=Twitter&Echobox=1557403852#xtor=CS2-4",
                        "display_url": "asiaone.com/singapore/sing\u2026"
                    }
                ],
                "annotations": [
                    {
                        "start": 0,
                        "end": 8,
                        "probability": 0.9349,
                        "type": "Place",
                        "normalized_text": "Singapore"
                    },
                    {
                        "start": 51,
                        "end": 58,
                        "probability": 0.9706,
                        "type": "Place",
                        "normalized_text": "Malaysia"
                    },
                    {
                        "start": 61,
                        "end": 74,
                        "probability": 0.8875,
                        "type": "Person",
                        "normalized_text": "Daim Zainuddin"
                    }
                ]
            },
            "lang": "en",
            "created_at": "2019-05-09T13:16:32.000Z",
            "public_metrics": {
                "retweet_count": 0,
                "reply_count": 0,
                "like_count": 0,
                "quote_count": 0
            },
            "id": "1126476044918300672",
            "text": "Singapore 'playing for time' in water dispute with Malaysia: Daim Zainuddin https://t.co/73vF8bogTx",
            "source": "Echobox",
            "possibly_sensitive": false,
            "reply_settings": "everyone"
        },
        "id": 1126476044918300672,
        "text": "Singapore 'playing for time' in water dispute with Malaysia: Daim Zainuddin https://t.co/73vF8bogTx",
        "attachments": null,
        "author_id": 19013879,
        "context_annotations": [],
        "conversation_id": 1126476044918300672,
        "created_at": "2019-05-09T13:16:32+00:00",
        "entities": {
            "urls": [
                {
                    "start": 76,
                    "end": 99,
                    "url": "https://t.co/73vF8bogTx",
                    "expanded_url": "https://www.asiaone.com/singapore/singapore-playing-time-water-dispute-malaysia-daim-zainuddin?utm_term=Autofeed&utm_medium=Social&utm_source=Twitter&Echobox=1557403852#xtor=CS2-4",
                    "display_url": "asiaone.com/singapore/sing\u2026"
                }
            ],
            "annotations": [
                {
                    "start": 0,
                    "end": 8,
                    "probability": 0.9349,
                    "type": "Place",
                    "normalized_text": "Singapore"
                },
                {
                    "start": 51,
                    "end": 58,
                    "probability": 0.9706,
                    "type": "Place",
                    "normalized_text": "Malaysia"
                },
                {
                    "start": 61,
                    "end": 74,
                    "probability": 0.8875,
                    "type": "Person",
                    "normalized_text": "Daim Zainuddin"
                }
            ]
        },
        "geo": null,
        "in_reply_to_user_id": null,
        "lang": "en",
        "non_public_metrics": null,
        "organic_metrics": null,
        "possibly_sensitive": false,
        "promoted_metrics": null,
        "public_metrics": {
            "retweet_count": 0,
            "reply_count": 0,
            "like_count": 0,
            "quote_count": 0
        },
        "referenced_tweets": null,
        "reply_settings": "everyone",
        "source": "Echobox",
        "withheld": null
    },
    {
        "data": {
            "author_id": "1073342248601960448",
            "conversation_id": "1126359603388846080",
            "entities": {
                "urls": [
                    {
                        "start": 74,
                        "end": 97,
                        "url": "https://t.co/ylPAfAey4S",
                        "expanded_url": "https://panpacificagency.com/news/southeast/05/09/analytics-singapore-playing-for-time-in-water-dispute-with-malaysia/",
                        "display_url": "panpacificagency.com/news/southeast\u2026"
                    }
                ],
                "hashtags": [
                    {
                        "start": 12,
                        "end": 22,
                        "tag": "Singapore"
                    },
                    {
                        "start": 64,
                        "end": 73,
                        "tag": "Malaysia"
                    }
                ]
            },
            "lang": "en",
            "created_at": "2019-05-09T05:33:50.000Z",
            "public_metrics": {
                "retweet_count": 0,
                "reply_count": 0,
                "like_count": 0,
                "quote_count": 0
            },
            "id": "1126359603388846080",
            "text": "[Analytics] #Singapore \u2018playing for time\u2019 in water dispute with #Malaysia https://t.co/ylPAfAey4S",
            "source": "Twitter Web Client",
            "possibly_sensitive": false,
            "reply_settings": "everyone"
        },
        "id": 1126359603388846080,
        "text": "[Analytics] #Singapore \u2018playing for time\u2019 in water dispute with #Malaysia https://t.co/ylPAfAey4S",
        "attachments": null,
        "author_id": 1073342248601960448,
        "context_annotations": [],
        "conversation_id": 1126359603388846080,
        "created_at": "2019-05-09T05:33:50+00:00",
        "entities": {
            "urls": [
                {
                    "start": 74,
                    "end": 97,
                    "url": "https://t.co/ylPAfAey4S",
                    "expanded_url": "https://panpacificagency.com/news/southeast/05/09/analytics-singapore-playing-for-time-in-water-dispute-with-malaysia/",
                    "display_url": "panpacificagency.com/news/southeast\u2026"
                }
            ],
            "hashtags": [
                {
                    "start": 12,
                    "end": 22,
                    "tag": "Singapore"
                },
                {
                    "start": 64,
                    "end": 73,
                    "tag": "Malaysia"
                }
            ]
        },
        "geo": null,
        "in_reply_to_user_id": null,
        "lang": "en",
        "non_public_metrics": null,
        "organic_metrics": null,
        "possibly_sensitive": false,
        "promoted_metrics": null,
        "public_metrics": {
            "retweet_count": 0,
            "reply_count": 0,
            "like_count": 0,
            "quote_count": 0
        },
        "referenced_tweets": null,
        "reply_settings": "everyone",
        "source": "Twitter Web Client",
        "withheld": null
    },
    {
        "data": {
            "author_id": "2555371945",
            "conversation_id": "1126342626569904128",
            "entities": {
                "urls": [
                    {
                        "start": 60,
                        "end": 83,
                        "url": "https://t.co/KISCQ0bMu9",
                        "expanded_url": "https://www.scmp.com/week-asia/politics/article/3009407/singapore-playing-time-water-dispute-malaysia-daim-zainuddin",
                        "display_url": "scmp.com/week-asia/poli\u2026"
                    }
                ],
                "annotations": [
                    {
                        "start": 0,
                        "end": 8,
                        "probability": 0.8647,
                        "type": "Place",
                        "normalized_text": "Singapore"
                    },
                    {
                        "start": 51,
                        "end": 58,
                        "probability": 0.9687,
                        "type": "Place",
                        "normalized_text": "Malaysia"
                    }
                ],
                "mentions": [
                    {
                        "start": 88,
                        "end": 97,
                        "username": "SCMPNews",
                        "id": "23922797"
                    }
                ]
            },
            "lang": "en",
            "created_at": "2019-05-09T04:26:23.000Z",
            "public_metrics": {
                "retweet_count": 0,
                "reply_count": 0,
                "like_count": 0,
                "quote_count": 0
            },
            "id": "1126342626569904128",
            "text": "Singapore \u2018playing for time\u2019 in water dispute with Malaysia https://t.co/KISCQ0bMu9 via @scmpnews",
            "source": "Twitter Web Client",
            "possibly_sensitive": false,
            "reply_settings": "everyone"
        },
        "id": 1126342626569904128,
        "text": "Singapore \u2018playing for time\u2019 in water dispute with Malaysia https://t.co/KISCQ0bMu9 via @scmpnews",
        "attachments": null,
        "author_id": 2555371945,
        "context_annotations": [],
        "conversation_id": 1126342626569904128,
        "created_at": "2019-05-09T04:26:23+00:00",
        "entities": {
            "urls": [
                {
                    "start": 60,
                    "end": 83,
                    "url": "https://t.co/KISCQ0bMu9",
                    "expanded_url": "https://www.scmp.com/week-asia/politics/article/3009407/singapore-playing-time-water-dispute-malaysia-daim-zainuddin",
                    "display_url": "scmp.com/week-asia/poli\u2026"
                }
            ],
            "annotations": [
                {
                    "start": 0,
                    "end": 8,
                    "probability": 0.8647,
                    "type": "Place",
                    "normalized_text": "Singapore"
                },
                {
                    "start": 51,
                    "end": 58,
                    "probability": 0.9687,
                    "type": "Place",
                    "normalized_text": "Malaysia"
                }
            ],
            "mentions": [
                {
                    "start": 88,
                    "end": 97,
                    "username": "SCMPNews",
                    "id": "23922797"
                }
            ]
        },
        "geo": null,
        "in_reply_to_user_id": null,
        "lang": "en",
        "non_public_metrics": null,
        "organic_metrics": null,
        "possibly_sensitive": false,
        "promoted_metrics": null,
        "public_metrics": {
            "retweet_count": 0,
            "reply_count": 0,
            "like_count": 0,
            "quote_count": 0
        },
        "referenced_tweets": null,
        "reply_settings": "everyone",
        "source": "Twitter Web Client",
        "withheld": null
    },
    {
        "data": {
            "author_id": "340287339",
            "conversation_id": "1126315060433911808",
            "entities": {
                "urls": [
                    {
                        "start": 60,
                        "end": 83,
                        "url": "https://t.co/fzN3ZDUpnO",
                        "expanded_url": "https://www.scmp.com/week-asia/politics/article/3009407/singapore-playing-time-water-dispute-malaysia-daim-zainuddin?utm_medium=Social&utm_source=Facebook#Echobox=1557315411",
                        "display_url": "scmp.com/week-asia/poli\u2026"
                    }
                ],
                "annotations": [
                    {
                        "start": 0,
                        "end": 8,
                        "probability": 0.8681,
                        "type": "Place",
                        "normalized_text": "Singapore"
                    },
                    {
                        "start": 51,
                        "end": 58,
                        "probability": 0.9747,
                        "type": "Place",
                        "normalized_text": "Malaysia"
                    }
                ]
            },
            "lang": "en",
            "created_at": "2019-05-09T02:36:50.000Z",
            "public_metrics": {
                "retweet_count": 0,
                "reply_count": 0,
                "like_count": 0,
                "quote_count": 0
            },
            "id": "1126315060433911808",
            "text": "Singapore \u2018playing for time\u2019 in water dispute with Malaysia https://t.co/fzN3ZDUpnO",
            "source": "Facebook",
            "possibly_sensitive": false,
            "reply_settings": "everyone"
        },
        "id": 1126315060433911808,
        "text": "Singapore \u2018playing for time\u2019 in water dispute with Malaysia https://t.co/fzN3ZDUpnO",
        "attachments": null,
        "author_id": 340287339,
        "context_annotations": [],
        "conversation_id": 1126315060433911808,
        "created_at": "2019-05-09T02:36:50+00:00",
        "entities": {
            "urls": [
                {
                    "start": 60,
                    "end": 83,
                    "url": "https://t.co/fzN3ZDUpnO",
                    "expanded_url": "https://www.scmp.com/week-asia/politics/article/3009407/singapore-playing-time-water-dispute-malaysia-daim-zainuddin?utm_medium=Social&utm_source=Facebook#Echobox=1557315411",
                    "display_url": "scmp.com/week-asia/poli\u2026"
                }
            ],
            "annotations": [
                {
                    "start": 0,
                    "end": 8,
                    "probability": 0.8681,
                    "type": "Place",
                    "normalized_text": "Singapore"
                },
                {
                    "start": 51,
                    "end": 58,
                    "probability": 0.9747,
                    "type": "Place",
                    "normalized_text": "Malaysia"
                }
            ]
        },
        "geo": null,
        "in_reply_to_user_id": null,
        "lang": "en",
        "non_public_metrics": null,
        "organic_metrics": null,
        "possibly_sensitive": false,
        "promoted_metrics": null,
        "public_metrics": {
            "retweet_count": 0,
            "reply_count": 0,
            "like_count": 0,
            "quote_count": 0
        },
        "referenced_tweets": null,
        "reply_settings": "everyone",
        "source": "Facebook",
        "withheld": null
    },
    {
        "data": {
            "author_id": "1028145588",
            "conversation_id": "1126228846267650048",
            "entities": {
                "urls": [
                    {
                        "start": 60,
                        "end": 83,
                        "url": "https://t.co/5b8F6coxJ1",
                        "expanded_url": "https://www.scmp.com/week-asia/politics/article/3009407/singapore-playing-time-water-dispute-malaysia-daim-zainuddin",
                        "display_url": "scmp.com/week-asia/poli\u2026"
                    }
                ],
                "annotations": [
                    {
                        "start": 0,
                        "end": 8,
                        "probability": 0.8647,
                        "type": "Place",
                        "normalized_text": "Singapore"
                    },
                    {
                        "start": 51,
                        "end": 58,
                        "probability": 0.9687,
                        "type": "Place",
                        "normalized_text": "Malaysia"
                    }
                ],
                "mentions": [
                    {
                        "start": 88,
                        "end": 97,
                        "username": "SCMPNews",
                        "id": "23922797"
                    }
                ]
            },
            "lang": "en",
            "created_at": "2019-05-08T20:54:15.000Z",
            "public_metrics": {
                "retweet_count": 0,
                "reply_count": 0,
                "like_count": 0,
                "quote_count": 0
            },
            "id": "1126228846267650048",
            "text": "Singapore \u2018playing for time\u2019 in water dispute with Malaysia https://t.co/5b8F6coxJ1 via @scmpnews",
            "source": "Twitter Web Client",
            "possibly_sensitive": false,
            "reply_settings": "everyone"
        },
        "id": 1126228846267650048,
        "text": "Singapore \u2018playing for time\u2019 in water dispute with Malaysia https://t.co/5b8F6coxJ1 via @scmpnews",
        "attachments": null,
        "author_id": 1028145588,
        "context_annotations": [],
        "conversation_id": 1126228846267650048,
        "created_at": "2019-05-08T20:54:15+00:00",
        "entities": {
            "urls": [
                {
                    "start": 60,
                    "end": 83,
                    "url": "https://t.co/5b8F6coxJ1",
                    "expanded_url": "https://www.scmp.com/week-asia/politics/article/3009407/singapore-playing-time-water-dispute-malaysia-daim-zainuddin",
                    "display_url": "scmp.com/week-asia/poli\u2026"
                }
            ],
            "annotations": [
                {
                    "start": 0,
                    "end": 8,
                    "probability": 0.8647,
                    "type": "Place",
                    "normalized_text": "Singapore"
                },
                {
                    "start": 51,
                    "end": 58,
                    "probability": 0.9687,
                    "type": "Place",
                    "normalized_text": "Malaysia"
                }
            ],
            "mentions": [
                {
                    "start": 88,
                    "end": 97,
                    "username": "SCMPNews",
                    "id": "23922797"
                }
            ]
        },
        "geo": null,
        "in_reply_to_user_id": null,
        "lang": "en",
        "non_public_metrics": null,
        "organic_metrics": null,
        "possibly_sensitive": false,
        "promoted_metrics": null,
        "public_metrics": {
            "retweet_count": 0,
            "reply_count": 0,
            "like_count": 0,
            "quote_count": 0
        },
        "referenced_tweets": null,
        "reply_settings": "everyone",
        "source": "Twitter Web Client",
        "withheld": null
    },
    {
        "data": {
            "author_id": "75342251",
            "conversation_id": "1126197759734894592",
            "entities": {
                "urls": [
                    {
                        "start": 87,
                        "end": 110,
                        "url": "https://t.co/jwiBBmn6aU",
                        "expanded_url": "https://singaporeinformer.com/360809/singapore-playing-for-time-in-water-dispute-with-malaysia-south-china-morning-post/",
                        "display_url": "singaporeinformer.com/360809/singapo\u2026"
                    },
                    {
                        "start": 111,
                        "end": 134,
                        "url": "https://t.co/txOOF168FL",
                        "expanded_url": "https://twitter.com/singaporeinform/status/1126197759734894592/photo/1",
                        "display_url": "pic.twitter.com/txOOF168FL"
                    }
                ],
                "annotations": [
                    {
                        "start": 0,
                        "end": 8,
                        "probability": 0.8935,
                        "type": "Place",
                        "normalized_text": "Singapore"
                    },
                    {
                        "start": 51,
                        "end": 58,
                        "probability": 0.9764,
                        "type": "Place",
                        "normalized_text": "Malaysia"
                    },
                    {
                        "start": 62,
                        "end": 72,
                        "probability": 0.7701,
                        "type": "Place",
                        "normalized_text": "South China"
                    }
                ]
            },
            "lang": "en",
            "created_at": "2019-05-08T18:50:44.000Z",
            "public_metrics": {
                "retweet_count": 0,
                "reply_count": 0,
                "like_count": 0,
                "quote_count": 0
            },
            "id": "1126197759734894592",
            "text": "Singapore \u2018playing for time\u2019 in water dispute with Malaysia \u2013 South China Morning\u00a0Post https://t.co/jwiBBmn6aU https://t.co/txOOF168FL",
            "source": "WordPress.com",
            "possibly_sensitive": false,
            "attachments": {
                "media_keys": [
                    "3_1126197758120157187"
                ]
            },
            "reply_settings": "everyone"
        },
        "id": 1126197759734894592,
        "text": "Singapore \u2018playing for time\u2019 in water dispute with Malaysia \u2013 South China Morning\u00a0Post https://t.co/jwiBBmn6aU https://t.co/txOOF168FL",
        "attachments": {
            "media_keys": [
                "3_1126197758120157187"
            ]
        },
        "author_id": 75342251,
        "context_annotations": [],
        "conversation_id": 1126197759734894592,
        "created_at": "2019-05-08T18:50:44+00:00",
        "entities": {
            "urls": [
                {
                    "start": 87,
                    "end": 110,
                    "url": "https://t.co/jwiBBmn6aU",
                    "expanded_url": "https://singaporeinformer.com/360809/singapore-playing-for-time-in-water-dispute-with-malaysia-south-china-morning-post/",
                    "display_url": "singaporeinformer.com/360809/singapo\u2026"
                },
                {
                    "start": 111,
                    "end": 134,
                    "url": "https://t.co/txOOF168FL",
                    "expanded_url": "https://twitter.com/singaporeinform/status/1126197759734894592/photo/1",
                    "display_url": "pic.twitter.com/txOOF168FL"
                }
            ],
            "annotations": [
                {
                    "start": 0,
                    "end": 8,
                    "probability": 0.8935,
                    "type": "Place",
                    "normalized_text": "Singapore"
                },
                {
                    "start": 51,
                    "end": 58,
                    "probability": 0.9764,
                    "type": "Place",
                    "normalized_text": "Malaysia"
                },
                {
                    "start": 62,
                    "end": 72,
                    "probability": 0.7701,
                    "type": "Place",
                    "normalized_text": "South China"
                }
            ]
        },
        "geo": null,
        "in_reply_to_user_id": null,
        "lang": "en",
        "non_public_metrics": null,
        "organic_metrics": null,
        "possibly_sensitive": false,
        "promoted_metrics": null,
        "public_metrics": {
            "retweet_count": 0,
            "reply_count": 0,
            "like_count": 0,
            "quote_count": 0
        },
        "referenced_tweets": null,
        "reply_settings": "everyone",
        "source": "WordPress.com",
        "withheld": null
    },
    {
        "data": {
            "author_id": "41542441",
            "conversation_id": "1126167879974412288",
            "entities": {
                "urls": [
                    {
                        "start": 76,
                        "end": 99,
                        "url": "https://t.co/YKtQFPpNL5",
                        "expanded_url": "https://www.scmp.com/week-asia/politics/article/3009407/singapore-playing-time-water-dispute-malaysia-daim-zainuddin",
                        "display_url": "scmp.com/week-asia/poli\u2026"
                    }
                ],
                "annotations": [
                    {
                        "start": 0,
                        "end": 8,
                        "probability": 0.8749,
                        "type": "Place",
                        "normalized_text": "Singapore"
                    },
                    {
                        "start": 51,
                        "end": 58,
                        "probability": 0.9682,
                        "type": "Place",
                        "normalized_text": "Malaysia"
                    },
                    {
                        "start": 61,
                        "end": 74,
                        "probability": 0.9051,
                        "type": "Person",
                        "normalized_text": "Daim Zainuddin"
                    }
                ]
            },
            "lang": "en",
            "created_at": "2019-05-08T16:52:00.000Z",
            "public_metrics": {
                "retweet_count": 0,
                "reply_count": 0,
                "like_count": 0,
                "quote_count": 0
            },
            "id": "1126167879974412288",
            "text": "Singapore \u2018playing for time\u2019 in water dispute with Malaysia: Daim Zainuddin https://t.co/YKtQFPpNL5",
            "source": "Twitter for iPhone",
            "possibly_sensitive": false,
            "reply_settings": "everyone"
        },
        "id": 1126167879974412288,
        "text": "Singapore \u2018playing for time\u2019 in water dispute with Malaysia: Daim Zainuddin https://t.co/YKtQFPpNL5",
        "attachments": null,
        "author_id": 41542441,
        "context_annotations": [],
        "conversation_id": 1126167879974412288,
        "created_at": "2019-05-08T16:52:00+00:00",
        "entities": {
            "urls": [
                {
                    "start": 76,
                    "end": 99,
                    "url": "https://t.co/YKtQFPpNL5",
                    "expanded_url": "https://www.scmp.com/week-asia/politics/article/3009407/singapore-playing-time-water-dispute-malaysia-daim-zainuddin",
                    "display_url": "scmp.com/week-asia/poli\u2026"
                }
            ],
            "annotations": [
                {
                    "start": 0,
                    "end": 8,
                    "probability": 0.8749,
                    "type": "Place",
                    "normalized_text": "Singapore"
                },
                {
                    "start": 51,
                    "end": 58,
                    "probability": 0.9682,
                    "type": "Place",
                    "normalized_text": "Malaysia"
                },
                {
                    "start": 61,
                    "end": 74,
                    "probability": 0.9051,
                    "type": "Person",
                    "normalized_text": "Daim Zainuddin"
                }
            ]
        },
        "geo": null,
        "in_reply_to_user_id": null,
        "lang": "en",
        "non_public_metrics": null,
        "organic_metrics": null,
        "possibly_sensitive": false,
        "promoted_metrics": null,
        "public_metrics": {
            "retweet_count": 0,
            "reply_count": 0,
            "like_count": 0,
            "quote_count": 0
        },
        "referenced_tweets": null,
        "reply_settings": "everyone",
        "source": "Twitter for iPhone",
        "withheld": null
    },
    {
        "data": {
            "author_id": "246109715",
            "conversation_id": "1126116372562554883",
            "entities": {
                "urls": [
                    {
                        "start": 76,
                        "end": 99,
                        "url": "https://t.co/rFgQB7RJLs",
                        "expanded_url": "http://bit.ly/2JmItAi",
                        "display_url": "bit.ly/2JmItAi"
                    }
                ],
                "annotations": [
                    {
                        "start": 0,
                        "end": 8,
                        "probability": 0.8749,
                        "type": "Place",
                        "normalized_text": "Singapore"
                    },
                    {
                        "start": 51,
                        "end": 58,
                        "probability": 0.9682,
                        "type": "Place",
                        "normalized_text": "Malaysia"
                    },
                    {
                        "start": 61,
                        "end": 74,
                        "probability": 0.9051,
                        "type": "Person",
                        "normalized_text": "Daim Zainuddin"
                    }
                ]
            },
            "lang": "en",
            "created_at": "2019-05-08T13:27:20.000Z",
            "public_metrics": {
                "retweet_count": 0,
                "reply_count": 0,
                "like_count": 0,
                "quote_count": 0
            },
            "id": "1126116372562554883",
            "text": "Singapore \u2018playing for time\u2019 in water dispute with Malaysia: Daim Zainuddin https://t.co/rFgQB7RJLs",
            "source": "IFTTT",
            "possibly_sensitive": false,
            "reply_settings": "everyone"
        },
        "id": 1126116372562554883,
        "text": "Singapore \u2018playing for time\u2019 in water dispute with Malaysia: Daim Zainuddin https://t.co/rFgQB7RJLs",
        "attachments": null,
        "author_id": 246109715,
        "context_annotations": [],
        "conversation_id": 1126116372562554883,
        "created_at": "2019-05-08T13:27:20+00:00",
        "entities": {
            "urls": [
                {
                    "start": 76,
                    "end": 99,
                    "url": "https://t.co/rFgQB7RJLs",
                    "expanded_url": "http://bit.ly/2JmItAi",
                    "display_url": "bit.ly/2JmItAi"
                }
            ],
            "annotations": [
                {
                    "start": 0,
                    "end": 8,
                    "probability": 0.8749,
                    "type": "Place",
                    "normalized_text": "Singapore"
                },
                {
                    "start": 51,
                    "end": 58,
                    "probability": 0.9682,
                    "type": "Place",
                    "normalized_text": "Malaysia"
                },
                {
                    "start": 61,
                    "end": 74,
                    "probability": 0.9051,
                    "type": "Person",
                    "normalized_text": "Daim Zainuddin"
                }
            ]
        },
        "geo": null,
        "in_reply_to_user_id": null,
        "lang": "en",
        "non_public_metrics": null,
        "organic_metrics": null,
        "possibly_sensitive": false,
        "promoted_metrics": null,
        "public_metrics": {
            "retweet_count": 0,
            "reply_count": 0,
            "like_count": 0,
            "quote_count": 0
        },
        "referenced_tweets": null,
        "reply_settings": "everyone",
        "source": "IFTTT",
        "withheld": null
    },
    {
        "data": {
            "author_id": "1090468264898002944",
            "conversation_id": "1126097124721078272",
            "entities": {
                "urls": [
                    {
                        "start": 61,
                        "end": 84,
                        "url": "https://t.co/s7kpmIJmbj",
                        "expanded_url": "https://www.scmp.com/week-asia/politics/article/3009407/singapore-playing-time-water-dispute-malaysia-daim-zainuddin",
                        "display_url": "scmp.com/week-asia/poli\u2026"
                    }
                ],
                "annotations": [
                    {
                        "start": 0,
                        "end": 8,
                        "probability": 0.8816,
                        "type": "Place",
                        "normalized_text": "Singapore"
                    },
                    {
                        "start": 51,
                        "end": 58,
                        "probability": 0.9276,
                        "type": "Place",
                        "normalized_text": "Malaysia"
                    }
                ]
            },
            "lang": "en",
            "created_at": "2019-05-08T12:10:51.000Z",
            "public_metrics": {
                "retweet_count": 0,
                "reply_count": 0,
                "like_count": 0,
                "quote_count": 0
            },
            "id": "1126097124721078272",
            "text": "Singapore \u2018playing for time\u2019 in water dispute with Malaysia\n\nhttps://t.co/s7kpmIJmbj",
            "source": "Twitter for Android",
            "possibly_sensitive": false,
            "reply_settings": "everyone"
        },
        "id": 1126097124721078272,
        "text": "Singapore \u2018playing for time\u2019 in water dispute with Malaysia\n\nhttps://t.co/s7kpmIJmbj",
        "attachments": null,
        "author_id": 1090468264898002944,
        "context_annotations": [],
        "conversation_id": 1126097124721078272,
        "created_at": "2019-05-08T12:10:51+00:00",
        "entities": {
            "urls": [
                {
                    "start": 61,
                    "end": 84,
                    "url": "https://t.co/s7kpmIJmbj",
                    "expanded_url": "https://www.scmp.com/week-asia/politics/article/3009407/singapore-playing-time-water-dispute-malaysia-daim-zainuddin",
                    "display_url": "scmp.com/week-asia/poli\u2026"
                }
            ],
            "annotations": [
                {
                    "start": 0,
                    "end": 8,
                    "probability": 0.8816,
                    "type": "Place",
                    "normalized_text": "Singapore"
                },
                {
                    "start": 51,
                    "end": 58,
                    "probability": 0.9276,
                    "type": "Place",
                    "normalized_text": "Malaysia"
                }
            ]
        },
        "geo": null,
        "in_reply_to_user_id": null,
        "lang": "en",
        "non_public_metrics": null,
        "organic_metrics": null,
        "possibly_sensitive": false,
        "promoted_metrics": null,
        "public_metrics": {
            "retweet_count": 0,
            "reply_count": 0,
            "like_count": 0,
            "quote_count": 0
        },
        "referenced_tweets": null,
        "reply_settings": "everyone",
        "source": "Twitter for Android",
        "withheld": null
    },
    {
        "data": {
            "author_id": "283604227",
            "conversation_id": "1126083599856357376",
            "entities": {
                "urls": [
                    {
                        "start": 76,
                        "end": 99,
                        "url": "https://t.co/2ehqKQeJAA",
                        "expanded_url": "https://www.scmp.com/week-asia/politics/article/3009407/singapore-playing-time-water-dispute-malaysia-daim-zainuddin?utm_source=dlvr.it&utm_medium=twitter",
                        "display_url": "scmp.com/week-asia/poli\u2026"
                    },
                    {
                        "start": 100,
                        "end": 123,
                        "url": "https://t.co/JqykTlif2G",
                        "expanded_url": "https://twitter.com/AndyVermaut/status/1126083599856357376/photo/1",
                        "display_url": "pic.twitter.com/JqykTlif2G"
                    }
                ],
                "annotations": [
                    {
                        "start": 0,
                        "end": 8,
                        "probability": 0.8783,
                        "type": "Place",
                        "normalized_text": "Singapore"
                    },
                    {
                        "start": 51,
                        "end": 58,
                        "probability": 0.9678,
                        "type": "Place",
                        "normalized_text": "Malaysia"
                    },
                    {
                        "start": 61,
                        "end": 74,
                        "probability": 0.909,
                        "type": "Person",
                        "normalized_text": "Daim Zainuddin"
                    }
                ]
            },
            "lang": "en",
            "created_at": "2019-05-08T11:17:06.000Z",
            "public_metrics": {
                "retweet_count": 0,
                "reply_count": 0,
                "like_count": 1,
                "quote_count": 0
            },
            "id": "1126083599856357376",
            "text": "Singapore \u2018playing for time\u2019 in water dispute with Malaysia: Daim Zainuddin https://t.co/2ehqKQeJAA https://t.co/JqykTlif2G",
            "source": "dlvr.it",
            "possibly_sensitive": false,
            "attachments": {
                "media_keys": [
                    "3_1126083598270943232"
                ]
            },
            "reply_settings": "everyone"
        },
        "id": 1126083599856357376,
        "text": "Singapore \u2018playing for time\u2019 in water dispute with Malaysia: Daim Zainuddin https://t.co/2ehqKQeJAA https://t.co/JqykTlif2G",
        "attachments": {
            "media_keys": [
                "3_1126083598270943232"
            ]
        },
        "author_id": 283604227,
        "context_annotations": [],
        "conversation_id": 1126083599856357376,
        "created_at": "2019-05-08T11:17:06+00:00",
        "entities": {
            "urls": [
                {
                    "start": 76,
                    "end": 99,
                    "url": "https://t.co/2ehqKQeJAA",
                    "expanded_url": "https://www.scmp.com/week-asia/politics/article/3009407/singapore-playing-time-water-dispute-malaysia-daim-zainuddin?utm_source=dlvr.it&utm_medium=twitter",
                    "display_url": "scmp.com/week-asia/poli\u2026"
                },
                {
                    "start": 100,
                    "end": 123,
                    "url": "https://t.co/JqykTlif2G",
                    "expanded_url": "https://twitter.com/AndyVermaut/status/1126083599856357376/photo/1",
                    "display_url": "pic.twitter.com/JqykTlif2G"
                }
            ],
            "annotations": [
                {
                    "start": 0,
                    "end": 8,
                    "probability": 0.8783,
                    "type": "Place",
                    "normalized_text": "Singapore"
                },
                {
                    "start": 51,
                    "end": 58,
                    "probability": 0.9678,
                    "type": "Place",
                    "normalized_text": "Malaysia"
                },
                {
                    "start": 61,
                    "end": 74,
                    "probability": 0.909,
                    "type": "Person",
                    "normalized_text": "Daim Zainuddin"
                }
            ]
        },
        "geo": null,
        "in_reply_to_user_id": null,
        "lang": "en",
        "non_public_metrics": null,
        "organic_metrics": null,
        "possibly_sensitive": false,
        "promoted_metrics": null,
        "public_metrics": {
            "retweet_count": 0,
            "reply_count": 0,
            "like_count": 1,
            "quote_count": 0
        },
        "referenced_tweets": null,
        "reply_settings": "everyone",
        "source": "dlvr.it",
        "withheld": null
    }
]