[
    {
        "data": {
            "referenced_tweets": [
                {
                    "type": "replied_to",
                    "id": "1437034298352209920"
                }
            ],
            "conversation_id": "1436914913855873028",
            "id": "1437053972192374784",
            "source": "Twitter Web App",
            "in_reply_to_user_id": "1347657267156549633",
            "author_id": "1390119716602056704",
            "entities": {
                "annotations": [
                    {
                        "start": 74,
                        "end": 77,
                        "probability": 0.4608,
                        "type": "Organization",
                        "normalized_text": "Army"
                    }
                ],
                "mentions": [
                    {
                        "start": 0,
                        "end": 16,
                        "username": "tiffanypriest99",
                        "id": "1347657267156549633"
                    },
                    {
                        "start": 17,
                        "end": 29,
                        "username": "bacchaus351",
                        "id": "3307309744"
                    },
                    {
                        "start": 30,
                        "end": 37,
                        "username": "pfizer",
                        "id": "56488059"
                    }
                ]
            },
            "lang": "en",
            "created_at": "2021-09-12T14:02:20.000Z",
            "reply_settings": "everyone",
            "text": "@tiffanypriest99 @bacchaus351 @pfizer Well, if one person that was in the Army says so based upon what is in their head, then it must be true.\n\nI'll go with history.\n\nAt most, the Code is a voluntary code of ethics. As a matter of law, it cannot be violated.",
            "context_annotations": [
                {
                    "domain": {
                        "id": "45",
                        "name": "Brand Vertical",
                        "description": "Top level entities that describe a Brands industry"
                    },
                    "entity": {
                        "id": "781974596740190208",
                        "name": "CPG"
                    }
                },
                {
                    "domain": {
                        "id": "46",
                        "name": "Brand Category",
                        "description": "Categories within Brand Verticals that narrow down the scope of Brands"
                    },
                    "entity": {
                        "id": "781974596752773120",
                        "name": "Pharma"
                    }
                },
                {
                    "domain": {
                        "id": "47",
                        "name": "Brand",
                        "description": "Brands and Companies"
                    },
                    "entity": {
                        "id": "10032761422",
                        "name": "Pfizer"
                    }
                }
            ],
            "possibly_sensitive": false,
            "public_metrics": {
                "retweet_count": 0,
                "reply_count": 0,
                "like_count": 1,
                "quote_count": 0
            }
        },
        "id": 1437053972192374784,
        "text": "@tiffanypriest99 @bacchaus351 @pfizer Well, if one person that was in the Army says so based upon what is in their head, then it must be true.\n\nI'll go with history.\n\nAt most, the Code is a voluntary code of ethics. As a matter of law, it cannot be violated.",
        "attachments": null,
        "author_id": 1390119716602056704,
        "context_annotations": [
            {
                "domain": {
                    "id": "45",
                    "name": "Brand Vertical",
                    "description": "Top level entities that describe a Brands industry"
                },
                "entity": {
                    "id": "781974596740190208",
                    "name": "CPG"
                }
            },
            {
                "domain": {
                    "id": "46",
                    "name": "Brand Category",
                    "description": "Categories within Brand Verticals that narrow down the scope of Brands"
                },
                "entity": {
                    "id": "781974596752773120",
                    "name": "Pharma"
                }
            },
            {
                "domain": {
                    "id": "47",
                    "name": "Brand",
                    "description": "Brands and Companies"
                },
                "entity": {
                    "id": "10032761422",
                    "name": "Pfizer"
                }
            }
        ],
        "conversation_id": 1436914913855873028,
        "created_at": "2021-09-12T14:02:20+00:00",
        "entities": {
            "annotations": [
                {
                    "start": 74,
                    "end": 77,
                    "probability": 0.4608,
                    "type": "Organization",
                    "normalized_text": "Army"
                }
            ],
            "mentions": [
                {
                    "start": 0,
                    "end": 16,
                    "username": "tiffanypriest99",
                    "id": "1347657267156549633"
                },
                {
                    "start": 17,
                    "end": 29,
                    "username": "bacchaus351",
                    "id": "3307309744"
                },
                {
                    "start": 30,
                    "end": 37,
                    "username": "pfizer",
                    "id": "56488059"
                }
            ]
        },
        "geo": null,
        "in_reply_to_user_id": 1347657267156549633,
        "lang": "en",
        "non_public_metrics": null,
        "organic_metrics": null,
        "possibly_sensitive": false,
        "promoted_metrics": null,
        "public_metrics": {
            "retweet_count": 0,
            "reply_count": 0,
            "like_count": 1,
            "quote_count": 0
        },
        "referenced_tweets": [
            {
                "data": {
                    "type": "replied_to",
                    "id": "1437034298352209920"
                },
                "id": 1437034298352209920,
                "type": "replied_to"
            }
        ],
        "reply_settings": "everyone",
        "source": "Twitter Web App",
        "withheld": null
    },
    {
        "data": {
            "referenced_tweets": [
                {
                    "type": "replied_to",
                    "id": "1436986515465322496"
                }
            ],
            "conversation_id": "1436914913855873028",
            "id": "1437017175311650820",
            "source": "TweetDeck Web App",
            "in_reply_to_user_id": "1347657267156549633",
            "author_id": "1390119716602056704",
            "lang": "en",
            "created_at": "2021-09-12T11:36:07.000Z",
            "reply_settings": "everyone",
            "text": "@tiffanypriest99 @bacchaus351 @pfizer The Code isn't law. It cannot be violated.",
            "context_annotations": [
                {
                    "domain": {
                        "id": "45",
                        "name": "Brand Vertical",
                        "description": "Top level entities that describe a Brands industry"
                    },
                    "entity": {
                        "id": "781974596740190208",
                        "name": "CPG"
                    }
                },
                {
                    "domain": {
                        "id": "46",
                        "name": "Brand Category",
                        "description": "Categories within Brand Verticals that narrow down the scope of Brands"
                    },
                    "entity": {
                        "id": "781974596752773120",
                        "name": "Pharma"
                    }
                },
                {
                    "domain": {
                        "id": "47",
                        "name": "Brand",
                        "description": "Brands and Companies"
                    },
                    "entity": {
                        "id": "10032761422",
                        "name": "Pfizer"
                    }
                }
            ],
            "entities": {
                "mentions": [
                    {
                        "start": 0,
                        "end": 16,
                        "username": "tiffanypriest99",
                        "id": "1347657267156549633"
                    },
                    {
                        "start": 17,
                        "end": 29,
                        "username": "bacchaus351",
                        "id": "3307309744"
                    },
                    {
                        "start": 30,
                        "end": 37,
                        "username": "pfizer",
                        "id": "56488059"
                    }
                ]
            },
            "possibly_sensitive": false,
            "public_metrics": {
                "retweet_count": 0,
                "reply_count": 1,
                "like_count": 0,
                "quote_count": 0
            }
        },
        "id": 1437017175311650820,
        "text": "@tiffanypriest99 @bacchaus351 @pfizer The Code isn't law. It cannot be violated.",
        "attachments": null,
        "author_id": 1390119716602056704,
        "context_annotations": [
            {
                "domain": {
                    "id": "45",
                    "name": "Brand Vertical",
                    "description": "Top level entities that describe a Brands industry"
                },
                "entity": {
                    "id": "781974596740190208",
                    "name": "CPG"
                }
            },
            {
                "domain": {
                    "id": "46",
                    "name": "Brand Category",
                    "description": "Categories within Brand Verticals that narrow down the scope of Brands"
                },
                "entity": {
                    "id": "781974596752773120",
                    "name": "Pharma"
                }
            },
            {
                "domain": {
                    "id": "47",
                    "name": "Brand",
                    "description": "Brands and Companies"
                },
                "entity": {
                    "id": "10032761422",
                    "name": "Pfizer"
                }
            }
        ],
        "conversation_id": 1436914913855873028,
        "created_at": "2021-09-12T11:36:07+00:00",
        "entities": {
            "mentions": [
                {
                    "start": 0,
                    "end": 16,
                    "username": "tiffanypriest99",
                    "id": "1347657267156549633"
                },
                {
                    "start": 17,
                    "end": 29,
                    "username": "bacchaus351",
                    "id": "3307309744"
                },
                {
                    "start": 30,
                    "end": 37,
                    "username": "pfizer",
                    "id": "56488059"
                }
            ]
        },
        "geo": null,
        "in_reply_to_user_id": 1347657267156549633,
        "lang": "en",
        "non_public_metrics": null,
        "organic_metrics": null,
        "possibly_sensitive": false,
        "promoted_metrics": null,
        "public_metrics": {
            "retweet_count": 0,
            "reply_count": 1,
            "like_count": 0,
            "quote_count": 0
        },
        "referenced_tweets": [
            {
                "data": {
                    "type": "replied_to",
                    "id": "1436986515465322496"
                },
                "id": 1436986515465322496,
                "type": "replied_to"
            }
        ],
        "reply_settings": "everyone",
        "source": "TweetDeck Web App",
        "withheld": null
    },
    {
        "data": {
            "referenced_tweets": [
                {
                    "type": "replied_to",
                    "id": "1436915653211041798"
                }
            ],
            "conversation_id": "1436914913855873028",
            "id": "1436915814695899138",
            "source": "Twitter for Android",
            "in_reply_to_user_id": "3307309744",
            "author_id": "3307309744",
            "entities": {
                "annotations": [
                    {
                        "start": 31,
                        "end": 36,
                        "probability": 0.9146,
                        "type": "Organization",
                        "normalized_text": "Pfizer"
                    }
                ],
                "mentions": [
                    {
                        "start": 0,
                        "end": 16,
                        "username": "tiffanypriest99",
                        "id": "1347657267156549633"
                    },
                    {
                        "start": 17,
                        "end": 24,
                        "username": "pfizer",
                        "id": "56488059"
                    }
                ]
            },
            "lang": "en",
            "created_at": "2021-09-12T04:53:21.000Z",
            "reply_settings": "everyone",
            "text": "@tiffanypriest99 @pfizer Also, Pfizer employees are mandated to get the vaccine unless exempt for medical reasons, in which case they are tested weekly in order to work.",
            "context_annotations": [
                {
                    "domain": {
                        "id": "65",
                        "name": "Interests and Hobbies Vertical",
                        "description": "Top level interests and hobbies groupings, like Food or Travel"
                    },
                    "entity": {
                        "id": "903303816698671104",
                        "name": "Wellness and health",
                        "description": "Wellness & Health"
                    }
                },
                {
                    "domain": {
                        "id": "66",
                        "name": "Interests and Hobbies Category",
                        "description": "A grouping of interests and hobbies entities, like Novelty Food or Destinations"
                    },
                    "entity": {
                        "id": "918538847302041600",
                        "name": "Community Health",
                        "description": "Community Health"
                    }
                },
                {
                    "domain": {
                        "id": "67",
                        "name": "Interests and Hobbies",
                        "description": "Interests, opinions, and behaviors of individuals, groups, or cultures; like Speciality Cooking or Theme Parks"
                    },
                    "entity": {
                        "id": "920768310152593408",
                        "name": "Common Medication",
                        "description": "Common Medication"
                    }
                },
                {
                    "domain": {
                        "id": "123",
                        "name": "Ongoing News Story",
                        "description": "Ongoing News Stories like 'Brexit'"
                    },
                    "entity": {
                        "id": "1220701888179359745",
                        "name": "COVID-19"
                    }
                },
                {
                    "domain": {
                        "id": "45",
                        "name": "Brand Vertical",
                        "description": "Top level entities that describe a Brands industry"
                    },
                    "entity": {
                        "id": "781974596740190208",
                        "name": "CPG"
                    }
                },
                {
                    "domain": {
                        "id": "46",
                        "name": "Brand Category",
                        "description": "Categories within Brand Verticals that narrow down the scope of Brands"
                    },
                    "entity": {
                        "id": "781974596752773120",
                        "name": "Pharma"
                    }
                },
                {
                    "domain": {
                        "id": "47",
                        "name": "Brand",
                        "description": "Brands and Companies"
                    },
                    "entity": {
                        "id": "10032761422",
                        "name": "Pfizer"
                    }
                }
            ],
            "possibly_sensitive": false,
            "public_metrics": {
                "retweet_count": 0,
                "reply_count": 3,
                "like_count": 0,
                "quote_count": 0
            }
        },
        "id": 1436915814695899138,
        "text": "@tiffanypriest99 @pfizer Also, Pfizer employees are mandated to get the vaccine unless exempt for medical reasons, in which case they are tested weekly in order to work.",
        "attachments": null,
        "author_id": 3307309744,
        "context_annotations": [
            {
                "domain": {
                    "id": "65",
                    "name": "Interests and Hobbies Vertical",
                    "description": "Top level interests and hobbies groupings, like Food or Travel"
                },
                "entity": {
                    "id": "903303816698671104",
                    "name": "Wellness and health",
                    "description": "Wellness & Health"
                }
            },
            {
                "domain": {
                    "id": "66",
                    "name": "Interests and Hobbies Category",
                    "description": "A grouping of interests and hobbies entities, like Novelty Food or Destinations"
                },
                "entity": {
                    "id": "918538847302041600",
                    "name": "Community Health",
                    "description": "Community Health"
                }
            },
            {
                "domain": {
                    "id": "67",
                    "name": "Interests and Hobbies",
                    "description": "Interests, opinions, and behaviors of individuals, groups, or cultures; like Speciality Cooking or Theme Parks"
                },
                "entity": {
                    "id": "920768310152593408",
                    "name": "Common Medication",
                    "description": "Common Medication"
                }
            },
            {
                "domain": {
                    "id": "123",
                    "name": "Ongoing News Story",
                    "description": "Ongoing News Stories like 'Brexit'"
                },
                "entity": {
                    "id": "1220701888179359745",
                    "name": "COVID-19"
                }
            },
            {
                "domain": {
                    "id": "45",
                    "name": "Brand Vertical",
                    "description": "Top level entities that describe a Brands industry"
                },
                "entity": {
                    "id": "781974596740190208",
                    "name": "CPG"
                }
            },
            {
                "domain": {
                    "id": "46",
                    "name": "Brand Category",
                    "description": "Categories within Brand Verticals that narrow down the scope of Brands"
                },
                "entity": {
                    "id": "781974596752773120",
                    "name": "Pharma"
                }
            },
            {
                "domain": {
                    "id": "47",
                    "name": "Brand",
                    "description": "Brands and Companies"
                },
                "entity": {
                    "id": "10032761422",
                    "name": "Pfizer"
                }
            }
        ],
        "conversation_id": 1436914913855873028,
        "created_at": "2021-09-12T04:53:21+00:00",
        "entities": {
            "annotations": [
                {
                    "start": 31,
                    "end": 36,
                    "probability": 0.9146,
                    "type": "Organization",
                    "normalized_text": "Pfizer"
                }
            ],
            "mentions": [
                {
                    "start": 0,
                    "end": 16,
                    "username": "tiffanypriest99",
                    "id": "1347657267156549633"
                },
                {
                    "start": 17,
                    "end": 24,
                    "username": "pfizer",
                    "id": "56488059"
                }
            ]
        },
        "geo": null,
        "in_reply_to_user_id": 3307309744,
        "lang": "en",
        "non_public_metrics": null,
        "organic_metrics": null,
        "possibly_sensitive": false,
        "promoted_metrics": null,
        "public_metrics": {
            "retweet_count": 0,
            "reply_count": 3,
            "like_count": 0,
            "quote_count": 0
        },
        "referenced_tweets": [
            {
                "data": {
                    "type": "replied_to",
                    "id": "1436915653211041798"
                },
                "id": 1436915653211041798,
                "type": "replied_to"
            }
        ],
        "reply_settings": "everyone",
        "source": "Twitter for Android",
        "withheld": null
    },
    {
        "data": {
            "referenced_tweets": [
                {
                    "type": "replied_to",
                    "id": "1436914913855873028"
                }
            ],
            "conversation_id": "1436914913855873028",
            "id": "1436915653211041798",
            "source": "Twitter for Android",
            "attachments": {
                "media_keys": [
                    "3_1436915650577027073"
                ]
            },
            "in_reply_to_user_id": "1347657267156549633",
            "author_id": "3307309744",
            "entities": {
                "annotations": [
                    {
                        "start": 64,
                        "end": 73,
                        "probability": 0.6472,
                        "type": "Organization",
                        "normalized_text": "Pfizer CEO"
                    }
                ],
                "urls": [
                    {
                        "start": 115,
                        "end": 138,
                        "url": "https://t.co/Dy9wVBG9cs",
                        "expanded_url": "https://twitter.com/bacchaus351/status/1436915653211041798/photo/1",
                        "display_url": "pic.twitter.com/Dy9wVBG9cs"
                    }
                ],
                "mentions": [
                    {
                        "start": 0,
                        "end": 16,
                        "username": "tiffanypriest99",
                        "id": "1347657267156549633"
                    },
                    {
                        "start": 17,
                        "end": 24,
                        "username": "pfizer",
                        "id": "56488059"
                    }
                ]
            },
            "lang": "en",
            "created_at": "2021-09-12T04:52:42.000Z",
            "reply_settings": "everyone",
            "text": "@tiffanypriest99 @pfizer Where did you hear that? Asking as the Pfizer CEO has been fully vaccinated for 6 months. https://t.co/Dy9wVBG9cs",
            "context_annotations": [
                {
                    "domain": {
                        "id": "123",
                        "name": "Ongoing News Story",
                        "description": "Ongoing News Stories like 'Brexit'"
                    },
                    "entity": {
                        "id": "1220701888179359745",
                        "name": "COVID-19"
                    }
                },
                {
                    "domain": {
                        "id": "45",
                        "name": "Brand Vertical",
                        "description": "Top level entities that describe a Brands industry"
                    },
                    "entity": {
                        "id": "781974596740190208",
                        "name": "CPG"
                    }
                },
                {
                    "domain": {
                        "id": "46",
                        "name": "Brand Category",
                        "description": "Categories within Brand Verticals that narrow down the scope of Brands"
                    },
                    "entity": {
                        "id": "781974596752773120",
                        "name": "Pharma"
                    }
                },
                {
                    "domain": {
                        "id": "47",
                        "name": "Brand",
                        "description": "Brands and Companies"
                    },
                    "entity": {
                        "id": "10032761422",
                        "name": "Pfizer"
                    }
                }
            ],
            "possibly_sensitive": false,
            "public_metrics": {
                "retweet_count": 0,
                "reply_count": 1,
                "like_count": 0,
                "quote_count": 0
            }
        },
        "id": 1436915653211041798,
        "text": "@tiffanypriest99 @pfizer Where did you hear that? Asking as the Pfizer CEO has been fully vaccinated for 6 months. https://t.co/Dy9wVBG9cs",
        "attachments": {
            "media_keys": [
                "3_1436915650577027073"
            ]
        },
        "author_id": 3307309744,
        "context_annotations": [
            {
                "domain": {
                    "id": "123",
                    "name": "Ongoing News Story",
                    "description": "Ongoing News Stories like 'Brexit'"
                },
                "entity": {
                    "id": "1220701888179359745",
                    "name": "COVID-19"
                }
            },
            {
                "domain": {
                    "id": "45",
                    "name": "Brand Vertical",
                    "description": "Top level entities that describe a Brands industry"
                },
                "entity": {
                    "id": "781974596740190208",
                    "name": "CPG"
                }
            },
            {
                "domain": {
                    "id": "46",
                    "name": "Brand Category",
                    "description": "Categories within Brand Verticals that narrow down the scope of Brands"
                },
                "entity": {
                    "id": "781974596752773120",
                    "name": "Pharma"
                }
            },
            {
                "domain": {
                    "id": "47",
                    "name": "Brand",
                    "description": "Brands and Companies"
                },
                "entity": {
                    "id": "10032761422",
                    "name": "Pfizer"
                }
            }
        ],
        "conversation_id": 1436914913855873028,
        "created_at": "2021-09-12T04:52:42+00:00",
        "entities": {
            "annotations": [
                {
                    "start": 64,
                    "end": 73,
                    "probability": 0.6472,
                    "type": "Organization",
                    "normalized_text": "Pfizer CEO"
                }
            ],
            "urls": [
                {
                    "start": 115,
                    "end": 138,
                    "url": "https://t.co/Dy9wVBG9cs",
                    "expanded_url": "https://twitter.com/bacchaus351/status/1436915653211041798/photo/1",
                    "display_url": "pic.twitter.com/Dy9wVBG9cs"
                }
            ],
            "mentions": [
                {
                    "start": 0,
                    "end": 16,
                    "username": "tiffanypriest99",
                    "id": "1347657267156549633"
                },
                {
                    "start": 17,
                    "end": 24,
                    "username": "pfizer",
                    "id": "56488059"
                }
            ]
        },
        "geo": null,
        "in_reply_to_user_id": 1347657267156549633,
        "lang": "en",
        "non_public_metrics": null,
        "organic_metrics": null,
        "possibly_sensitive": false,
        "promoted_metrics": null,
        "public_metrics": {
            "retweet_count": 0,
            "reply_count": 1,
            "like_count": 0,
            "quote_count": 0
        },
        "referenced_tweets": [
            {
                "data": {
                    "type": "replied_to",
                    "id": "1436914913855873028"
                },
                "id": 1436914913855873028,
                "type": "replied_to"
            }
        ],
        "reply_settings": "everyone",
        "source": "Twitter for Android",
        "withheld": null
    }
]